django_ups_tnt-1.0.1.dist-info/DESCRIPTION.rst
django_ups_tnt-1.0.1.dist-info/METADATA
django_ups_tnt-1.0.1.dist-info/RECORD
django_ups_tnt-1.0.1.dist-info/WHEEL
django_ups_tnt-1.0.1.dist-info/metadata.json
django_ups_tnt-1.0.1.dist-info/top_level.txt
ups_tnt/__init__.py
ups_tnt/apps.py
ups_tnt/exceptions.py
ups_tnt/serializers.py
ups_tnt/settings.py
ups_tnt/tasks.py
ups_tnt/tnt.py
ups_tnt/urls.py
ups_tnt/views.py
