Metadata-Version: 2.0
Name: django-ups-tnt
Version: 1.0.1
Summary: Django wrapper around UPS Time In Transit JSON API
Home-page: https://gitlab.com/thelabnyc/django-ups-tnt
Author: David Burke
Author-email: dburke@thelabnyc.com
License: ISC
Platform: UNKNOWN
Classifier: Development Status :: 5 - Production/Stable
Classifier: Environment :: Web Environment
Classifier: Framework :: Django
Classifier: Framework :: Django :: 1.8
Classifier: Framework :: Django :: 1.9
Classifier: Intended Audience :: Developers
Classifier: License :: OSI Approved :: ISC License (ISCL)
Classifier: Operating System :: Unix
Classifier: Programming Language :: Python
Classifier: Programming Language :: Python :: 3
Classifier: Programming Language :: Python :: 3.5
Requires-Dist: Django (>=1.8.11)
Requires-Dist: djangorestframework (>=3.3.3)
Requires-Dist: python-dateutil (>=2.5.2)
Requires-Dist: requests (>=2.9.1)
